s3dl/__init__.py
s3dl/__main__.py
s3dl/s3dl.py
s3dl-0.1.0.dist-info/DESCRIPTION.rst
s3dl-0.1.0.dist-info/METADATA
s3dl-0.1.0.dist-info/RECORD
s3dl-0.1.0.dist-info/WHEEL
s3dl-0.1.0.dist-info/entry_points.txt
s3dl-0.1.0.dist-info/metadata.json
s3dl-0.1.0.dist-info/pbr.json
s3dl-0.1.0.dist-info/top_level.txt
