Metadata-Version: 2.0
Name: s3dl
Version: 0.1.0
Summary: Makes downloading s3 files easier
Home-page: UNKNOWN
Author: Will Gardner
Author-email: will.gardner@couchbase.com
License: MIT
Platform: UNKNOWN
Requires-Dist: boto3
